bw2scaffold/__init__.py
bw2scaffold/cli.py
bw2scaffold/directories.py
bw2scaffold/plugins.py
bw2scaffold/prepare.py
bw2scaffold/visualization.py
bw2scaffold/bw2utils/__init__.py
bw2scaffold/bw2utils/datamodels.py
bw2scaffold/bw2utils/logging.py
bw2scaffold/bw2utils/protocols.py
bw2scaffold/bw2utils/validators.py
bw2scaffold/bw2utils/visualization.py
bw2scaffold/examples/run_example.py
bw2scaffold/templates/.gitignore.template
bw2scaffold/templates/README.md.src.analysis.template
bw2scaffold/templates/README.md.src.assets.template
bw2scaffold/templates/README.md.src.data.private.template
bw2scaffold/templates/README.md.src.data.processed.template
bw2scaffold/templates/README.md.src.data.raw.template
bw2scaffold/templates/README.md.src.modeling.template
bw2scaffold/templates/README.md.src.processing.template
bw2scaffold/templates/README.md.template
bw2scaffold/templates/directories.yaml
bw2scaffold/templates/environment.yaml.template
bw2scaffold/templates/requirements.txt.template
bw2scaffold/templates/run.py.src.template
bw2scaffold-0.0.7.post1.dev9.dist-info/licenses/LICENSE.txt
bw2scaffold-0.0.7.post1.dev9.dist-info/METADATA
bw2scaffold-0.0.7.post1.dev9.dist-info/WHEEL
bw2scaffold-0.0.7.post1.dev9.dist-info/entry_points.txt
bw2scaffold-0.0.7.post1.dev9.dist-info/top_level.txt
bw2scaffold-0.0.7.post1.dev9.dist-info/RECORD
