Metadata-Version: 2.4
Name: bw2scaffold
Version: 0.0.7.post1.dev9
Summary: bw2scaffold is a templating tool that can facilitate the development of Life Cycle Oriented studies.
Home-page: https://git.list.lu/gustavo.larrea/replicable-lca
Author: Gustavo Larrea
Author-email: gustavo.larrea@list.lu
License: MIT
Project-URL: Documentation, https://git.list.lu/gustavo.larrea/replicable-lca
Project-URL: Source, https://git.list.lu/gustavo.larrea/replicable-lca
Project-URL: Changelog, https://git.list.lu/gustavo.larrea/replicable-lca/-/blob/main/CHANGELOG.rst?ref_type=heads
Project-URL: Tracker, https://git.list.lu/gustavo.larrea/replicable-lca/issues
Platform: any
Classifier: Development Status :: 4 - Beta
Classifier: Programming Language :: Python
Classifier: Programming Language :: Python :: 3 :: Only
Classifier: Programming Language :: Python :: 3.10
Classifier: Programming Language :: Python :: 3.11
Classifier: Programming Language :: Python :: 3.12
Requires-Python: >3.9
License-File: LICENSE.txt
Requires-Dist: typer
Requires-Dist: PyYAML
Requires-Dist: jinja2
Requires-Dist: pydantic
Requires-Dist: mypy
Requires-Dist: types-PyYAML
Requires-Dist: code2flow
Requires-Dist: python-dotenv
Provides-Extra: testing
Requires-Dist: setuptools; extra == "testing"
Requires-Dist: pytest; extra == "testing"
Requires-Dist: pytest-cov; extra == "testing"
Provides-Extra: dev
Requires-Dist: pre-commit; extra == "dev"
Requires-Dist: pylint; extra == "dev"
Dynamic: license-file
